compling/__init__.py
compling/config.ini
compling/config.py
compling/default_config.ini
compling/descriptor.py
compling/nlp.py
compling/embeddings/__init__.py
compling/embeddings/embeddings.py
compling/embeddings/documents/__init__.py
compling/embeddings/documents/dembeddings.py
compling/embeddings/documents/impl/__init__.py
compling/embeddings/documents/impl/doc2vec.py
compling/embeddings/words/__init__.py
compling/embeddings/words/wembeddings.py
compling/embeddings/words/impl/__init__.py
compling/embeddings/words/impl/fasttext.py
compling/embeddings/words/impl/word2vec.py
compling/example-corpus/vatican-publications/Benedict XV/Apost_exhortations/Fummo Chiamati.json
compling/example-corpus/vatican-publications/Benedict XV/Apost_letters/Maximum Illud.json
compling/example-corpus/vatican-publications/Benedict XV/Encyclicals/Ad Beatissimi Apostolorum.json
compling/example-corpus/vatican-publications/Benedict XV/Encyclicals/Annus Iam Plenus.json
compling/example-corpus/vatican-publications/Benedict XV/Encyclicals/Fausto Appetente Die.json
compling/example-corpus/vatican-publications/Benedict XV/Encyclicals/Humani Generis Redemptionem.json
compling/example-corpus/vatican-publications/Benedict XV/Encyclicals/In Hac Tanta.json
compling/example-corpus/vatican-publications/Benedict XV/Encyclicals/In Praeclara Summorum.json
compling/example-corpus/vatican-publications/Benedict XV/Encyclicals/Pacem Dei Munus Pulcherrimum.json
compling/example-corpus/vatican-publications/Benedict XV/Encyclicals/Paterno Iam Diu.json
compling/example-corpus/vatican-publications/Benedict XV/Encyclicals/Principi Apostolorum Petro.json
compling/example-corpus/vatican-publications/Benedict XV/Encyclicals/Quod Iam Diu.json
compling/example-corpus/vatican-publications/Benedict XV/Encyclicals/Sacra Propediem.json
compling/example-corpus/vatican-publications/Benedict XV/Encyclicals/Spiritus Paraclitus.json
compling-0.0.38.dist-info/METADATA
compling-0.0.38.dist-info/WHEEL
compling-0.0.38.dist-info/top_level.txt
compling-0.0.38.dist-info/RECORD
