Metadata-Version: 2.1
Name: compling
Version: 0.0.38
Summary: Computational Linguistic
Home-page: https://github.com/FrancescoPeriti/compling
Author: Francesco Periti
Author-email: peritifrancesco@gmail.com
License: UNKNOWN
Platform: UNKNOWN
Classifier: Programming Language :: Python :: 3
Classifier: License :: OSI Approved :: MIT License
Classifier: Operating System :: OS Independent
Requires-Python: >=3.6
